README.md
app.py
setup.cfg
setup.py
rogit.egg-info/PKG-INFO
rogit.egg-info/SOURCES.txt
rogit.egg-info/dependency_links.txt
rogit.egg-info/entry_points.txt
rogit.egg-info/requires.txt
rogit.egg-info/top_level.txt