Metadata-Version: 2.1
Name: rogit
Version: 1.1.1
Summary: This is a little git automation for lazy devs. Add, commit and push in one single command.
Home-page: https://github.com/roeeyn/rogit
Author: roeeyn
Author-email: rodrigo.medina.neri@gmail.com
License: MIT
Download-URL: https://github.com/roeeyn/rogit/releases/download/1.0/rogit-1.0.tar.gz
Keywords: git,automation
Platform: UNKNOWN
Classifier: Development Status :: 5 - Production/Stable
Classifier: Intended Audience :: Developers
Classifier: Topic :: Software Development :: Build Tools
Classifier: License :: OSI Approved :: MIT License
Classifier: Programming Language :: Python :: 3
Classifier: Programming Language :: Python :: 3.4
Classifier: Programming Language :: Python :: 3.5
Classifier: Programming Language :: Python :: 3.6
